describeai/__init__.py
describeai/api_resources/__init__.py
describeai/api_resources/code_summarization.py
describeai-0.5.2.dist-info/METADATA
describeai-0.5.2.dist-info/WHEEL
describeai-0.5.2.dist-info/top_level.txt
describeai-0.5.2.dist-info/RECORD
